LICENSE.md
README.md
setup.py
askai/__init__.py
askai/constants.py
askai/entrypoint_askai.py
askai/entrypoint_config.py
askai/entrypoint_init.py
askai/entrypoint_key.py
askai/utils.py
askai.egg-info/PKG-INFO
askai.egg-info/SOURCES.txt
askai.egg-info/dependency_links.txt
askai.egg-info/entry_points.txt
askai.egg-info/requires.txt
askai.egg-info/top_level.txt