Metadata-Version: 2.1
Name: askai
Version: 1.0.5
Summary: Your simple terminal helper
Home-page: https://github.com/maxvfischer/askai
Download-URL: https://github.com/maxvfischer/askai/archive/refs/tags/v1.0.5.tar.gz
Author: Max Fischer
License: MIT
License-File: LICENSE.md
